decode_things/__init__.py
decode_things/decode.py
decode_things/encode.py
Decode_Things-0.0.6.dist-info/LICENSE
Decode_Things-0.0.6.dist-info/METADATA
Decode_Things-0.0.6.dist-info/WHEEL
Decode_Things-0.0.6.dist-info/top_level.txt
Decode_Things-0.0.6.dist-info/RECORD
