Metadata-Version: 2.1
Name: Decode-Things
Version: 0.0.6
Summary: A package that allows to decode and encode code.
Author-email: JustWait <justwaitnano@gmail.com>
License: MIT License
Project-URL: Homepage, https://github.com/justwaitfor-me/decode_things/
Keywords: Decode Things,decode,decoding,decode_things,code,hex,bin,binary,url,object,python,decode url,pypi,encode,encodeing
Classifier: Development Status :: 3 - Alpha
Classifier: Operating System :: OS Independent
Classifier: License :: OSI Approved :: MIT License
Classifier: Programming Language :: Python
Classifier: Programming Language :: Python :: 3
Requires-Python: >=3.5
License-File: LICENSE
Requires-Dist: termcolor
Requires-Dist: requests
Requires-Dist: xmltodict
